wslogtail/__init__.py
wslogtail-1.0.1.dist-info/DESCRIPTION.rst
wslogtail-1.0.1.dist-info/METADATA
wslogtail-1.0.1.dist-info/RECORD
wslogtail-1.0.1.dist-info/WHEEL
wslogtail-1.0.1.dist-info/entry_points.txt
wslogtail-1.0.1.dist-info/metadata.json
wslogtail-1.0.1.dist-info/top_level.txt
