Metadata-Version: 2.0
Name: wslogtail
Version: 1.0.1
Summary: Log tail, from redis pubsub to logfile buffer and websocket streaming.
Home-page: https://gitlab.clarisys.fr/common/wslogtail
Author: Laurent COUSTET
Author-email: laurent.coustet@clarisys.fr
License: UNKNOWN
Platform: UNKNOWN
Requires-Dist: websockets
Requires-Dist: ansi2html
Requires-Dist: asyncio-redis
